fbscribelogger/__init__.py
fbscribelogger-0.1.7.dist-info/LICENSE
fbscribelogger-0.1.7.dist-info/METADATA
fbscribelogger-0.1.7.dist-info/WHEEL
fbscribelogger-0.1.7.dist-info/RECORD
