Metadata-Version: 2.1
Name: fbscribelogger
Version: 0.1.7
Summary: 
License: MIT
Author: Edward Z. Yang
Author-email: ezyang@meta.com
Requires-Python: >=3.8.1
Classifier: License :: OSI Approved :: MIT License
Classifier: Operating System :: OS Independent
Classifier: Programming Language :: Python :: 3
Classifier: Programming Language :: Python :: 3.9
Classifier: Programming Language :: Python :: 3.10
Classifier: Programming Language :: Python :: 3.11
Classifier: Programming Language :: Python :: 3.12
Requires-Dist: aiohttp (>=3.10.4,<4.0.0)
Requires-Dist: thriftpy2 (>=0.5.2,<0.6.0)
Requires-Dist: typing-extensions (>=4.12.2,<5.0.0)
